amazon_bedrock_cli/__init__.py
amazon_bedrock_cli/bedrock.py
amazon_bedrock_cli/cli.py
amazon_bedrock_cli/commands/__init__.py
amazon_bedrock_cli/commands/list.py
amazon_bedrock_cli/commands/run.py
amazon_bedrock_cli-0.0.1.dev0.dist-info/METADATA
amazon_bedrock_cli-0.0.1.dev0.dist-info/WHEEL
amazon_bedrock_cli-0.0.1.dev0.dist-info/entry_points.txt
amazon_bedrock_cli-0.0.1.dev0.dist-info/licenses/LICENSE
amazon_bedrock_cli-0.0.1.dev0.dist-info/RECORD
