Metadata-Version: 2.4
Name: amazon-bedrock-cli
Version: 0.0.1.dev0
Summary: A CLI tool for Amazon Bedrock
Project-URL: Source, https://github.com/DennisTraub/amazon-bedrock-cli-python
Author-email: Dennis Traub <dennis.traub@gmail.com>
License: MIT
License-File: LICENSE
Classifier: Development Status :: 2 - Pre-Alpha
Classifier: Intended Audience :: Developers
Classifier: License :: OSI Approved :: MIT License
Classifier: Natural Language :: English
Classifier: Programming Language :: Python
Classifier: Programming Language :: Python :: 3
Classifier: Programming Language :: Python :: 3 :: Only
Requires-Python: >=3.8
Requires-Dist: amazon-bedrock>=0.0.5
Requires-Dist: click>=8.1.8
